<?xml version="1.0" encoding="UTF-8"?>
<actions>
<action>
	<icon>utilities-terminal</icon>
	<name>Open Terminal Here</name>
	<submenu></submenu>
	<unique-id>1748759188394440-1</unique-id>
	<command>exo-open --working-directory %f --launch TerminalEmulator</command>
	<description>Example for a custom action</description>
	<range></range>
	<patterns>*</patterns>
	<startup-notify/>
	<directories/>
</action>
<action>
	<icon>document-preview</icon>
	<name>Quick Preview</name>
	<submenu></submenu>
	<unique-id>1748759188394440-2</unique-id>
	<command>gloobus-preview %f</command>
	<description>Preview file with Gloobus</description>
	<range></range>
	<patterns>*</patterns>
	<audio-files/>
	<image-files/>
	<other-files/>
	<text-files/>
	<video-files/>
</action>
</actions>
